utilityman/__init__.py
utilityman/cli.py
utilityman-0.4.0.dist-info/METADATA
utilityman-0.4.0.dist-info/WHEEL
utilityman-0.4.0.dist-info/entry_points.txt
utilityman-0.4.0.dist-info/licenses/LICENSE
utilityman-0.4.0.dist-info/RECORD
