Metadata-Version: 2.4
Name: utilityman
Version: 0.4.0
Summary: Follow any MLB game in your shell - the utility player for baseball fans
Project-URL: Homepage, https://github.com/stiles/utilityman
Project-URL: Repository, https://github.com/stiles/utilityman
Project-URL: Issues, https://github.com/stiles/utilityman/issues
Author: Matt Stiles
License: MIT
License-File: LICENSE
Keywords: baseball,cli,live,mlb,sports
Classifier: Environment :: Console
Classifier: Intended Audience :: End Users/Desktop
Classifier: License :: OSI Approved :: MIT License
Classifier: Programming Language :: Python :: 3
Classifier: Programming Language :: Python :: 3 :: Only
Classifier: Topic :: Games/Entertainment
Classifier: Topic :: Utilities
Requires-Python: >=3.9
Requires-Dist: requests>=2.31
